CHANGES.rst
CONTRIBUTORS.rst
LICENSE.rst
MANIFEST.in
README.rst
setup.cfg
setup.py
docs/index.rst
src/collective/__init__.py
src/collective.pantry.egg-info/PKG-INFO
src/collective.pantry.egg-info/SOURCES.txt
src/collective.pantry.egg-info/dependency_links.txt
src/collective.pantry.egg-info/entry_points.txt
src/collective.pantry.egg-info/namespace_packages.txt
src/collective.pantry.egg-info/not-zip-safe
src/collective.pantry.egg-info/requires.txt
src/collective.pantry.egg-info/top_level.txt
src/collective/pantry/__init__.py
src/collective/pantry/configure.zcml
src/collective/pantry/interfaces.py
src/collective/pantry/setuphandlers.py
src/collective/pantry/testing.py
src/collective/pantry/browser/__init__.py
src/collective/pantry/browser/configure.zcml
src/collective/pantry/browser/pantry.pt
src/collective/pantry/browser/pantry.py
src/collective/pantry/browser/raw.pt
src/collective/pantry/browser/tiny_pantry.py
src/collective/pantry/browser/overrides/.gitkeep
src/collective/pantry/browser/static/.gitkeep
src/collective/pantry/locales/collective.pantry.pot
src/collective/pantry/locales/update.sh
src/collective/pantry/profiles/default/browserlayer.xml
src/collective/pantry/profiles/default/metadata.xml
src/collective/pantry/profiles/default/registry.xml
src/collective/pantry/profiles/default/types.xml
src/collective/pantry/profiles/default/types/Snippet.xml
src/collective/pantry/profiles/uninstall/browserlayer.xml
src/collective/pantry/tests/__init__.py
src/collective/pantry/tests/test_robot.py
src/collective/pantry/tests/test_setup.py
src/collective/pantry/tests/test_snippet.py
src/collective/pantry/tests/robot/test_example.robot
src/collective/pantry/tests/robot/test_snippet.robot