Metadata-Version: 1.1
Name: collective.pantry
Version: 1.0a1
Summary: An add-on for Plone
Home-page: https://pypi.python.org/pypi/collective.pantry
Author: Victor Fernandez de Alba
Author-email: sneridagh@gmail.com
License: GPL version 2
Keywords: Python Plone
Platform: UNKNOWN
Classifier: Environment :: Web Environment
Classifier: Framework :: Plone
Classifier: Framework :: Plone :: 5.0
Classifier: Programming Language :: Python
Classifier: Programming Language :: Python :: 2.7
Classifier: Operating System :: OS Independent
Classifier: License :: OSI Approved :: GNU General Public License v2 (GPLv2)
